pyDH/__init__.py
pyDH/pyDH.py
pyDH-0.1.6.dist-info/LICENSE
pyDH-0.1.6.dist-info/METADATA
pyDH-0.1.6.dist-info/WHEEL
pyDH-0.1.6.dist-info/top_level.txt
pyDH-0.1.6.dist-info/RECORD
