Metadata-Version: 2.1
Name: pyDH
Version: 0.1.6
Summary: Pure Python Implementation of Diffie-Hellman Key Exchange
Home-page: https://github.com/amiralis/pyDH
Author: Amirali Sanatinia
Author-email: amirali@ccs.neu.edu
License: Apache
Keywords: crypto,Diffie Hellman,Key Exchange
Platform: UNKNOWN
Classifier: License :: OSI Approved :: Apache Software License
Classifier: Programming Language :: Python :: 2.7
Classifier: Programming Language :: Python :: 3.2
Classifier: Programming Language :: Python :: 3.3
Classifier: Programming Language :: Python :: 3.4
Classifier: Programming Language :: Python :: 3.5
Classifier: Topic :: Security :: Cryptography
